{
  "id": 406,
  "title": "Buzzer Beater",
  "title_jp": "BUZZER BEATER",
  "slug": "buzzer-beater",
  "type": "legendados",
  "format": "TV",
  "images": {
    "poster": "https://cdn.myanimelist.net/images/anime/6/57421l.webp",
    "banner": "https://cdn.myanimelist.net/images/anime/6/57421.jpg"
  },
  "trailer": null,
  "synopsis": "Hideyoshi is a homeless boy living in New York in the near future, who survives by hustling other kids in basketball games. But now he's been drafted into a pro team-a pro team with a very unique goal. There once was a time when humans dominated the game of basketball. But times have changed, and now the physically superior alien players have taken over the game, and there are barely any human players left. But Hideyoshi's team-the first all-human team to compete in the Space League-intends to change all that, and bring the championship back home to Earth.\n\n(Source: ANN)",
  "score": 6.49,
  "genres": [
    "Sci-Fi",
    "Sports"
  ],
  "episodes": [
    {
      "numero": 1,
      "url": "https://lightspeedst.net/s3/mp4/buzzer-beater/sd/1.mp4",
      "nome": "Throw In"
    },
    {
      "numero": 2,
      "url": "https://lightspeedst.net/s3/mp4/buzzer-beater/sd/2.mp4",
      "nome": "Transition"
    },
    {
      "numero": 3,
      "url": "https://www.blogger.com/video.g?token=AD6v5dzbCZnS1Q71SazUqLHwY9AlKWusWJDaiSLBtFwBMW2aLNJVLTJ3r8ARdhdc4XsySNArbN8lZtd-vIA432YBAmDUa1WX5gRhsGQN8ASoRGWZ_UNG5Qk0W84fMf_RoRbycXAieeVD",
      "nome": "Chucker"
    },
    {
      "numero": 4,
      "url": "https://lightspeedst.net/s3/mp4/buzzer-beater/sd/4.mp4",
      "nome": "PG"
    },
    {
      "numero": 5,
      "url": "https://lightspeedst.net/s3/mp4/buzzer-beater/sd/5.mp4",
      "nome": "Tip-Off"
    },
    {
      "numero": 6,
      "url": "https://lightspeedst.net/s3/mp4/buzzer-beater/sd/6.mp4",
      "nome": "Charging"
    },
    {
      "numero": 7,
      "url": "https://lightspeedst.net/s3/mp4/buzzer-beater/sd/7.mp4",
      "nome": "Sixth Man"
    },
    {
      "numero": 8,
      "url": "https://lightspeedst.net/s3/mp4/buzzer-beater/sd/8.mp4",
      "nome": "Fast Break"
    },
    {
      "numero": 9,
      "url": "https://lightspeedst.net/s3/mp4/buzzer-beater/sd/9.mp4",
      "nome": "Triple Double"
    },
    {
      "numero": 10,
      "url": "https://lightspeedst.net/s3/mp4/buzzer-beater/sd/10.mp4",
      "nome": "J"
    },
    {
      "numero": 11,
      "url": "https://lightspeedst.net/s3/mp4/buzzer-beater/sd/11.mp4",
      "nome": "Hang Time"
    },
    {
      "numero": 12,
      "url": "https://lightspeedst.net/s3/mp4/buzzer-beater/sd/12.mp4",
      "nome": "Clutch Shot"
    },
    {
      "numero": 13,
      "url": "https://lightspeedst.net/s3/mp4/buzzer-beater/sd/13.mp4",
      "nome": "Buzzer Beater"
    }
  ]
}