{
  "id": 41461,
  "title": "Date A Live IV",
  "title_jp": "デート・ア・ライブⅣ",
  "slug": "date-a-live-iv",
  "type": "legendados",
  "format": "TV",
  "images": {
    "poster": "https://cdn.myanimelist.net/images/anime/1368/121281l.webp",
    "banner": "https://cdn.myanimelist.net/images/anime/1368/121281.jpg"
  },
  "trailer": "https://www.youtube-nocookie.com/embed/-7ICd6g2Gak?enablejsapi=1&wmode=opaque&autoplay=1",
  "synopsis": "Despite the numerous challenges he has overcome so far, Shidou Itsuka's mission with Ratatoskr is far from over. In a departure from his daily routine, Shidou encounters a starving woman lying on the street and ends up helping her. After the two arrive at her apartment, the woman introduces herself as Nia Honjou—a popular manga artist working under a pen name. However, cutting straight to the chase, Nia reveals that she is also a Spirit and is aware of Shidou's secret operation.\n\nInterested in seeing his charisma firsthand, Nia challenges Shidou to win her over on a date. As he strives for an opportunity to seal her powers, Shidou learns more about Nia and her history with Deus Ex Machina Industries, a name he is all too familiar with...\n\n[Written by MAL Rewrite]",
  "score": 7.73,
  "genres": [
    "Action",
    "Fantasy",
    "Romance",
    "Sci-Fi"
  ],
  "episodes": [
    {
      "numero": 1,
      "url": "https://lightspeedst.net/s1/mp4/date-a-live-iv/sd/1.mp4",
      "nome": "Don't Panic. This is a Spirit Trap."
    },
    {
      "numero": 2,
      "url": "https://lightspeedst.net/s1/mp4/date-a-live-iv/hd/2.mp4",
      "nome": "So Be It, 2D It Is."
    },
    {
      "numero": 3,
      "url": "https://lightspeedst.net/s1/mp4/date-a-live-iv/hd/3.mp4",
      "nome": "What's Yours Is Mine."
    },
    {
      "numero": 4,
      "url": "https://lightspeedst.net/s1/mp4/date-a-live-iv/fhd/4.mp4",
      "nome": "The Spirit From Space."
    },
    {
      "numero": 5,
      "url": "https://lightspeedst.net/s1/mp4/date-a-live-iv/fhd/5.mp4",
      "nome": "Fairy Tale"
    }
  ]
}