{
  "id": 1928,
  "title": "Early Reins",
  "title_jp": "アーリーレインズ",
  "slug": "early-reins",
  "type": "legendados",
  "format": "OVA",
  "images": {
    "poster": "https://cdn.myanimelist.net/images/anime/1/1928l.webp",
    "banner": "https://cdn.myanimelist.net/images/anime/1/1928.jpg"
  },
  "trailer": null,
  "synopsis": "Margaret Hart is a young woman who dreams of becoming a sheriff in the American West following the Civil War. When she boards a train to the next town over and prepares to relax, she gets caught up in a hijacking attempt by a group of bandits composed of former Confederate soldiers. After being taken hostage, Margaret teams up with the other captive women to fight back against the outlaws.\n\n[Written by MAL Rewrite]",
  "score": 5.92,
  "genres": [
    "Action",
    "Adventure"
  ],
  "episodes": [
    {
      "numero": 1,
      "url": "https://lightspeedst.net/s2/mp4/early-reins/sd/1.mp4"
    }
  ]
}