{
  "id": 49909,
  "title": "Kotarou wa Hitorigurashi (Dublado)",
  "title_jp": "コタローは1人暮らし",
  "slug": "kotarou-wa-hitorigurashi-dublado",
  "type": "dublados",
  "format": "ONA",
  "images": {
    "poster": "https://cdn.myanimelist.net/images/anime/1862/121020l.webp",
    "banner": "https://cdn.myanimelist.net/images/anime/1862/121020.jpg"
  },
  "trailer": "https://www.youtube-nocookie.com/embed/0XJA93kdzsQ?enablejsapi=1&wmode=opaque&autoplay=1",
  "synopsis": "One day, manga author Shin Karino is greeted by four-year-old Kotarou Satou, his new next-door neighbor, who gifts him a box of tissues. In Karino's eyes, Kotarou is an odd kid: he speaks in an extremely formal manner, and he lives alone in his apartment—no parents or relatives in sight. But Kotarou neither seems to mind, nor wants to rely on people.\n\nFeeling sympathetic toward Kotarou's circumstances, Karino decides to follow Kotarou to a bathhouse in case something might happen to him and there he comes to understand the little boy is not so different from him. Little by little, Karino—along with the other residents of the apartment complex—grows fond of Kotarou and his antics. At the same time, Kotarou himself might have found something akin to a family in his unique neighbors.\n\n[Written by MAL Rewrite]",
  "score": 8.15,
  "genres": [
    "Slice of Life"
  ],
  "episodes": [
    {
      "numero": 1,
      "url": "https://lightspeedst.net/s1/mp4/kotarou-wa-hitorigurashi-dublado/hd/1.mp4"
    },
    {
      "numero": 2,
      "url": "https://lightspeedst.net/s1/mp4/kotarou-wa-hitorigurashi-dublado/hd/2.mp4"
    },
    {
      "numero": 3,
      "url": "https://lightspeedst.net/s1/mp4/kotarou-wa-hitorigurashi-dublado/hd/3.mp4"
    },
    {
      "numero": 4,
      "url": "https://lightspeedst.net/s1/mp4/kotarou-wa-hitorigurashi-dublado/hd/4.mp4"
    },
    {
      "numero": 5,
      "url": "https://lightspeedst.net/s1/mp4/kotarou-wa-hitorigurashi-dublado/hd/5.mp4"
    },
    {
      "numero": 6,
      "url": "https://lightspeedst.net/s1/mp4/kotarou-wa-hitorigurashi-dublado/hd/6.mp4"
    },
    {
      "numero": 7,
      "url": "https://lightspeedst.net/s1/mp4/kotarou-wa-hitorigurashi-dublado/hd/7.mp4"
    },
    {
      "numero": 8,
      "url": "https://lightspeedst.net/s1/mp4/kotarou-wa-hitorigurashi-dublado/sd/8.mp4"
    },
    {
      "numero": 9,
      "url": "https://lightspeedst.net/s1/mp4/kotarou-wa-hitorigurashi-dublado/hd/9.mp4"
    },
    {
      "numero": 10,
      "url": "https://lightspeedst.net/s1/mp4/kotarou-wa-hitorigurashi-dublado/hd/10.mp4"
    }
  ]
}