{
  "id": 6115,
  "title": "Lupin III vs. Detective Conan",
  "title_jp": "ルパン三世 vs 名探偵コナン",
  "slug": "lupin-iii-vs-detective-conan",
  "type": "legendados",
  "format": "TV Special",
  "images": {
    "poster": "https://cdn.myanimelist.net/images/anime/1849/134190l.webp",
    "banner": "https://cdn.myanimelist.net/images/anime/1849/134190.jpg"
  },
  "trailer": null,
  "synopsis": "In a country called Vesparand, a new mineral with super stealth properties has been discovered which attracts Lupin's attention. At the same time the untimely deaths of Queen Sakura and her son, Prince Gill, leave Princess Mira next in succession to the throne. During a trip to Japan, Princess Mira finds her double in Ran and takes the opportunity to trade places, which ends with Ran being spirited away to Vesparand with Conan, Zenigata, Kogoro Mouri, Lupin and Fujiko in tow. There they meet a waiting Jigen and solve the mystery of the deaths of the Queen and Prince.\n\n(Source: ANN)",
  "score": 7.75,
  "genres": [
    "Action",
    "Adventure",
    "Comedy",
    "Mystery"
  ],
  "episodes": [
    {
      "numero": 1,
      "url": "https://lightspeedst.net/s3/mp4/lupin-iii-vs-detective-conan/sd/1.mp4"
    }
  ]
}