{
  "id": 3225,
  "title": "Minami-ke Okawari",
  "title_jp": "みなみけ～おかわり～",
  "slug": "minami-ke-okawari",
  "type": "legendados",
  "format": "TV",
  "images": {
    "poster": "https://cdn.myanimelist.net/images/anime/10/73556l.webp",
    "banner": "https://cdn.myanimelist.net/images/anime/10/73556.jpg"
  },
  "trailer": "https://www.youtube-nocookie.com/embed/3tb6Z-kQep0?enablejsapi=1&wmode=opaque&autoplay=1",
  "synopsis": "A new year has started, and the three Minami sisters—Haruka, Kana, and Chiaki—are still living together without adult supervision. As the seasons pass, the girls continue to make friends and find new interests. No matter where they are or who they hang out with, the sisters' time remains ever vibrant.\n\n[Written by MAL Rewrite]",
  "score": 7.32,
  "genres": [
    "Comedy"
  ],
  "episodes": [
    {
      "numero": 1,
      "url": "https://lightspeedst.net/s3/mp4/minami-ke-okawari/sd/1.mp4",
      "nome": "Hot Springs, Let's Eat"
    },
    {
      "numero": 2,
      "url": "https://lightspeedst.net/s3/mp4/minami-ke-okawari/sd/2.mp4",
      "nome": "Taste is Something Inherited Over Generations"
    },
    {
      "numero": 3,
      "url": "https://lightspeedst.net/s3/mp4/minami-ke-okawari/sd/3.mp4",
      "nome": "Evening Hospitality, Hesitantly Offered"
    },
    {
      "numero": 4,
      "url": "https://lightspeedst.net/s3/mp4/minami-ke-okawari/sd/4.mp4",
      "nome": "Is It All Right to Clean Up?"
    },
    {
      "numero": 5,
      "url": "https://lightspeedst.net/s3/mp4/minami-ke-okawari/sd/5.mp4",
      "nome": "Can't Take Back a Served Tea Cup"
    },
    {
      "numero": 6,
      "url": "https://lightspeedst.net/s3/mp4/minami-ke-okawari/sd/6.mp4",
      "nome": "Has My Rice Cooled Down"
    },
    {
      "numero": 7,
      "url": "https://lightspeedst.net/s3/mp4/minami-ke-okawari/sd/7.mp4",
      "nome": "The More You Chew It, The Sweeter It Becomes"
    },
    {
      "numero": 8,
      "url": "https://lightspeedst.net/s3/mp4/minami-ke-okawari/sd/8.mp4",
      "nome": "There's Always Time for the Pool"
    },
    {
      "numero": 9,
      "url": "https://lightspeedst.net/s3/mp4/minami-ke-okawari/sd/9.mp4",
      "nome": "Does It Hurt Yet? Secrets of Mako-chan"
    },
    {
      "numero": 10,
      "url": "https://lightspeedst.net/s3/mp4/minami-ke-okawari/sd/10.mp4",
      "nome": "The Age of Dangos over Flowers"
    },
    {
      "numero": 11,
      "url": "https://lightspeedst.net/s3/mp4/minami-ke-okawari/sd/11.mp4",
      "nome": "As Expected, It's Getting Bad"
    },
    {
      "numero": 12,
      "url": "https://lightspeedst.net/s3/mp4/minami-ke-okawari/sd/12.mp4",
      "nome": "Even One Bite More Is Painful"
    },
    {
      "numero": 13,
      "url": "https://lightspeedst.net/s3/mp4/minami-ke-okawari/sd/13.mp4",
      "nome": "Everyone At Once, 'Thank You for the Meal"
    }
  ]
}