{
  "id": 601,
  "title": "Nekojiru-sou",
  "title_jp": "ねこぢる草",
  "slug": "nekojiru-sou",
  "type": "legendados",
  "format": "OVA",
  "images": {
    "poster": "https://cdn.myanimelist.net/images/anime/5/84241l.webp",
    "banner": "https://cdn.myanimelist.net/images/anime/5/84241.jpg"
  },
  "trailer": null,
  "synopsis": "The main character, a cat named Nyatto, embarks upon a journey to save his sister's soul, which was ripped in two when Nyatto tried to save her from Death. She trails after him, brain-dead. They encounter many brilliant, mind-bending situations, beginning with a disturbing magic show.\n\n(Source: ANN)",
  "score": 7.32,
  "genres": [
    "Avant Garde",
    "Award Winning",
    "Comedy"
  ],
  "episodes": [
    {
      "numero": 1,
      "url": "https://lightspeedst.net/s2/mp4/nekojiru-sou/sd/1.mp4"
    }
  ]
}