{
  "id": 58197,
  "title": "Nyaight of the Living Cat",
  "title_jp": "ニャイト・オブ・ザ・リビングキャット",
  "slug": "nyaight-of-the-living-cat",
  "type": "legendados",
  "format": "TV",
  "images": {
    "poster": "https://cdn.myanimelist.net/images/anime/1411/150445l.webp",
    "banner": "https://cdn.myanimelist.net/images/anime/1411/150445.jpg"
  },
  "trailer": "https://www.youtube-nocookie.com/embed/4REA4evnf5M?enablejsapi=1&wmode=opaque&autoplay=1",
  "synopsis": "In the 21st century, humanity's love for cats grew so deep that nearly everyone owns one as a pet. However, selective breeding of cats results in an extraordinary individual who carries a strange virus. The outbreak—dubbed the Nyandemic—turns any human who makes contact with an infected feline into one themselves.\n\nKunagi, a man who has lost all of his memories, is forced to flee mid-shift from a cat cafe. With him are siblings who run the place, Gaku and Kaoru, and a customer named Tanishi. But Gaku confesses that he is already infected and pleads with Kunagi to protect his sister. After experiencing the danger firsthand, the remaining three begin searching for a way to survive the very animals they adore.\n\nDespite the government's best efforts to halt the feline hordes, the Nyandemic uncontrollably spreads. Human extinction seems more probable by the hour—but Kunagi, Kaoru, and Tanishi refuse to surrender their humanity without a fight!\n\n[Written by MAL Rewrite]",
  "score": 6.33,
  "genres": [
    "Action",
    "Horror",
    "Suspense"
  ],
  "episodes": [
    {
      "numero": 1,
      "url": "https://lightspeedst.net/s5/mp4/nyaight-of-the-living-cat/hd/1.mp4",
      "nome": "Everything Becomes Cat"
    },
    {
      "numero": 2,
      "url": "https://lightspeedst.net/s5/mp4_temp/nyaight-of-the-living-cat/2/720p.mp4",
      "nome": "Tonight the Cats Steal the Stars"
    },
    {
      "numero": 3,
      "url": "https://lightspeedst.net/s5/mp4/nyaight-of-the-living-cat/hd/3.mp4",
      "nome": "Cats in Prison"
    },
    {
      "numero": 4,
      "url": "https://lightspeedst.net/s5/mp4_temp/nyaight-of-the-living-cat/4/720p.mp4",
      "nome": "The Cat Is a Harsh Master"
    },
    {
      "numero": 5,
      "url": "https://lightspeedst.net/s5/mp4/nyaight-of-the-living-cat/hd/5.mp4",
      "nome": "Cat Max"
    },
    {
      "numero": 6,
      "url": "https://lightspeedst.net/s5/mp4/nyaight-of-the-living-cat/hd/6.mp4",
      "nome": "Cat Rising"
    },
    {
      "numero": 7,
      "url": "https://lightspeedst.net/s5/mp4_temp/nyaight-of-the-living-cat/7/720p.mp4",
      "nome": "The Feline D-REX from Another World"
    },
    {
      "numero": 8,
      "url": "https://lightspeedst.net/s5/mp4_temp/nyaight-of-the-living-cat/8/720p.mp4",
      "nome": "Nyarmageddon"
    },
    {
      "numero": 9,
      "url": "https://lightspeedst.net/s5/mp4_temp/nyaight-of-the-living-cat/9/720p.mp4",
      "nome": "Commeowndo"
    },
    {
      "numero": 10,
      "url": "https://lightspeedst.net/s5/mp4_temp/nyaight-of-the-living-cat/10/720p.mp4",
      "nome": "Norwegian d'Arc"
    },
    {
      "numero": 11,
      "url": "https://lightspeedst.net/s5/mp4_temp/nyaight-of-the-living-cat/11/720p.mp4",
      "nome": "Transformeows"
    },
    {
      "numero": 12,
      "url": "https://lightspeedst.net/s5/mp4/nyaight-of-the-living-cat/hd/12.mp4",
      "nome": "Meow Am Legend"
    }
  ]
}