{
  "id": 59846,
  "title": "Saigo ni Hitotsu dake Onegai shitemo Yoroshii deshou ka",
  "title_jp": "最後にひとつだけお願いしてもよろしいでしょうか",
  "slug": "saigo-ni-hitotsu-dake-onegai-shitemo-yoroshii-deshou-ka",
  "type": "legendados",
  "format": "TV",
  "images": {
    "poster": "https://cdn.myanimelist.net/images/anime/1190/151754l.webp",
    "banner": "https://cdn.myanimelist.net/images/anime/1190/151754.jpg"
  },
  "trailer": "https://www.youtube-nocookie.com/embed/E-txbaNATrU?enablejsapi=1&wmode=opaque&autoplay=1",
  "synopsis": "Ever since childhood, Scarlet El Vandimion has preferred to deal with wrongdoers by using her fists. However, to preserve her family's image, she suppresses her instincts and tolerates the abuse inflicted by her childish fiancé, Second Prince Kyle Von Pallistan. Only Kyle's brother, First Prince Julius, is aware that there is more to Scarlet than meets the eye, but she cares little about his growing interest.\n\nIn the middle of a ball, Kyle accuses Scarlet of harassing Terenezza Hopkins, a commoner that has taken his heart. Scarlet's engagement to Kyle is nullified, leaving her outraged that all of her efforts to endure thus far have amounted to nothing. Scarlet dons her studded leather gloves, once again becoming the \"Mad Dog Princess.\" Joined by Julius and werebeast Nanaka, Scarlet is ready to give filthy nobles a taste of their own medicine—one punch at a time.\n\n[Written by MAL Rewrite]",
  "score": 7.46,
  "genres": [
    "Action",
    "Comedy",
    "Fantasy",
    "Romance"
  ],
  "episodes": [
    {
      "numero": 1,
      "url": "https://lightspeedst.net/s5/mp4_temp/saigo-ni-hitotsu-dake-onegai-shitemo-yoroshii-deshou-ka/1/720p.mp4",
      "nome": "May I Kindly Beat the Tar Out of Those Evil Nobles (Pigs)?"
    },
    {
      "numero": 2,
      "url": "https://lightspeedst.net/s5/mp4_temp/saigo-ni-hitotsu-dake-onegai-shitemo-yoroshii-deshou-ka/2/720p.mp4",
      "nome": "May I Offer You the Taste of My Fist as the Ladylike Thing to Do?"
    },
    {
      "numero": 3,
      "url": "https://lightspeedst.net/s5/mp4_temp/saigo-ni-hitotsu-dake-onegai-shitemo-yoroshii-deshou-ka/3/720p.mp4",
      "nome": "I Considered a Negotiated Resolution, but May I Biff and Pow Those Noblemen Instead?"
    },
    {
      "numero": 4,
      "url": "https://lightspeedst.net/s5/mp4/saigo-ni-hitotsu-dake-onegai-shitemo-yoroshii-deshou-ka/hd/4.mp4",
      "nome": "May I Go to See My Fists' Beloved One (Punching Bag)?"
    },
    {
      "numero": 5,
      "url": "https://lightspeedst.net/s5/mp4/saigo-ni-hitotsu-dake-onegai-shitemo-yoroshii-deshou-ka/hd/5.mp4",
      "nome": "May I Clobber this Asshole Prince?"
    },
    {
      "numero": 6,
      "url": "https://lightspeedst.net/s5/mp4/saigo-ni-hitotsu-dake-onegai-shitemo-yoroshii-deshou-ka/hd/6.mp4",
      "nome": "May I Send This Pig Flying Into the Sky?"
    },
    {
      "numero": 7,
      "url": "https://lightspeedst.net/s5/mp4/saigo-ni-hitotsu-dake-onegai-shitemo-yoroshii-deshou-ka/hd/7.mp4",
      "nome": "May I Carry Out a Plan That Shows a New Side of You?"
    },
    {
      "numero": 8,
      "url": "https://lightspeedst.net/s5/mp4/saigo-ni-hitotsu-dake-onegai-shitemo-yoroshii-deshou-ka/hd/8.mp4",
      "nome": "May I Offer You a Fist in Place of a Handkerchief?"
    },
    {
      "numero": 9,
      "url": "https://lightspeedst.net/s5/mp4/saigo-ni-hitotsu-dake-onegai-shitemo-yoroshii-deshou-ka/hd/9.mp4",
      "nome": "May I Explain That This Is Not Something That Just Anyone Can Do?"
    },
    {
      "numero": 10,
      "url": "https://lightspeedst.net/s2/mp4/saigo-ni-hitotsu-dake-onegai-shitemo-yoroshii-deshou-ka/hd/10.mp4",
      "nome": "May I Cook This Thick Cut of Pork Through With Body Punches?"
    },
    {
      "numero": 11,
      "url": "https://lightspeedst.net/s2/mp4/saigo-ni-hitotsu-dake-onegai-shitemo-yoroshii-deshou-ka/hd/11.mp4",
      "nome": "As These Appear Undercooked, May I Turn Them Into Mince Meat?"
    }
  ]
}