{
  "id": 39617,
  "title": "Yakusoku no Neverland 2nd Season",
  "title_jp": "約束のネバーランド",
  "slug": "yakusoku-no-neverland-2nd-season",
  "type": "legendados",
  "format": "TV",
  "images": {
    "poster": "https://cdn.myanimelist.net/images/anime/1815/110626l.webp",
    "banner": "https://cdn.myanimelist.net/images/anime/1815/110626.jpg"
  },
  "trailer": "https://www.youtube-nocookie.com/embed/TAU4PFKxqxo?enablejsapi=1&wmode=opaque&autoplay=1",
  "synopsis": "Emma, Ray, and the rest of the older children have escaped the confines of the Grace Field House. However, with relentless demons set on capturing them, their arduous battle for freedom has only just begun.\n\nDespite venturing into the treacherous wilderness, the children remain optimistic due to their possession of books written by William Minerva. Coded within his books are messages detailing the world outside the farm—information that can help them survive with the limited resources they have. But when their pursuers draw near, the children soon encounter their most dreadful situation yet. \n\nIn Yakusoku no Neverland 2nd Season, the children struggle to survive in the strange ruthless world, striving to find a sanctuary they can truly call home.\n\n[Written by MAL Rewrite]",
  "score": 5.25,
  "genres": [
    "Mystery",
    "Suspense"
  ],
  "episodes": [
    {
      "numero": 1,
      "url": "https://lightspeedst.net/s2/mp4/yakusoku-no-neverland-2nd-season/hd/1.mp4",
      "nome": "Episode 1"
    },
    {
      "numero": 2,
      "url": "https://lightspeedst.net/s2/mp4/yakusoku-no-neverland-2nd-season/hd/2.mp4",
      "nome": "Episode 2"
    },
    {
      "numero": 3,
      "url": "https://lightspeedst.net/s2/mp4/yakusoku-no-neverland-2nd-season/hd/3.mp4",
      "nome": "Episode 3"
    },
    {
      "numero": 4,
      "url": "https://lightspeedst.net/s4/mp4/yakusoku-no-neverland-2nd-season/sd/4.mp4",
      "nome": "Episode 4"
    },
    {
      "numero": 5,
      "url": "https://www.blogger.com/video.g?token=AD6v5dwBD4T9_h6RfPLYdvzCwskhKDITqubpMewe92v_a6ieEKGF5BFl7V-GpbBUSaWkcVgO_hO6prBucZiZYwQBXTjRqS2TxBNpxUEsW5We4_fojccqsX9GmLiQiDoKnRV0uGg1CwyH",
      "nome": "Episode 5"
    },
    {
      "numero": 6,
      "url": "https://lightspeedst.net/s3/mp4/yakusoku-no-neverland-2nd-season/hd/6.mp4",
      "nome": "Episode 6"
    },
    {
      "numero": 7,
      "url": "https://lightspeedst.net/s2/mp4/yakusoku-no-neverland-2nd-season/hd/7.mp4",
      "nome": "Episode 7"
    },
    {
      "numero": 8,
      "url": "https://lightspeedst.net/s2/mp4/yakusoku-no-neverland-2nd-season/hd/8.mp4",
      "nome": "Episode 8"
    },
    {
      "numero": 9,
      "url": "https://lightspeedst.net/s2/mp4/yakusoku-no-neverland-2nd-season/hd/9.mp4",
      "nome": "Episode 9"
    },
    {
      "numero": 10,
      "url": "https://lightspeedst.net/s2/mp4/yakusoku-no-neverland-2nd-season/hd/10.mp4",
      "nome": "Episode 10"
    },
    {
      "numero": 11,
      "url": "https://lightspeedst.net/s2/mp4/yakusoku-no-neverland-2nd-season/hd/11.mp4",
      "nome": "Episode 11"
    }
  ]
}