{
  "id": 41660,
  "title": "Yesterday wo Utatte Haishin-ban Episode",
  "title_jp": "イエスタデイをうたって 配信版エピソード",
  "slug": "yesterday-wo-utatte-haishin-ban-episode",
  "type": "legendados",
  "format": "ONA",
  "images": {
    "poster": "https://cdn.myanimelist.net/images/anime/1919/107275l.webp",
    "banner": "https://cdn.myanimelist.net/images/anime/1919/107275.jpg"
  },
  "trailer": null,
  "synopsis": "While Shinako Morinome spends the quietest hours of each night reminiscing about her late friend, Rikuo Uozumi's monotonous days gain a little bit of color due to Haru Nonaka's bright presence. Although he pretends to be indifferent, Rikuo is thankful for how Haru changes his life.\n\n[Written by MAL Rewrite]",
  "score": 6.62,
  "genres": [
    "Drama",
    "Romance"
  ],
  "episodes": [
    {
      "numero": 1,
      "url": "https://lightspeedst.net/s3/mp4/yesterday-wo-utatte-haishin-ban-episode/hd/1.mp4"
    },
    {
      "numero": 2,
      "url": "https://lightspeedst.net/s3/mp4/yesterday-wo-utatte-haishin-ban-episode/hd/2.mp4"
    },
    {
      "numero": 3,
      "url": "https://lightspeedst.net/s3/mp4/yesterday-wo-utatte-haishin-ban-episode/hd/3.mp4"
    },
    {
      "numero": 4,
      "url": "https://lightspeedst.net/s3/mp4/yesterday-wo-utatte-haishin-ban-episode/hd/4.mp4"
    },
    {
      "numero": 5,
      "url": "https://lightspeedst.net/s3/mp4/yesterday-wo-utatte-haishin-ban-episode/hd/5.mp4"
    },
    {
      "numero": 6,
      "url": "https://lightspeedst.net/s3/mp4/yesterday-wo-utatte-haishin-ban-episode/hd/6.mp4"
    }
  ]
}